gitlab_client-0.0.1.dev5.dist-info/top_level.txt
gitlab_client-0.0.1.dev5.dist-info/entry_points.txt
gitlab_client-0.0.1.dev5.dist-info/DESCRIPTION.rst
gitlab_client-0.0.1.dev5.dist-info/RECORD
gitlab_client-0.0.1.dev5.dist-info/METADATA
gitlab_client-0.0.1.dev5.dist-info/pbr.json
gitlab_client-0.0.1.dev5.dist-info/metadata.json
gitlab_client-0.0.1.dev5.dist-info/WHEEL
issues/__init__.py
issues/shell.py
client/__init__.py
client/shell.py
