Metadata-Version: 2.0
Name: gitlab-client
Version: 0.0.1.dev5
Summary: Simple GitLab client
Home-page: http://gbraad.nl/
Author: Gerard Braad
Author-email: me@gbraad.nl
License: UNKNOWN
Platform: UNKNOWN
Classifier: Intended Audience :: Information Technology
Classifier: Intended Audience :: Developers
Classifier: License :: OSI Approved :: Apache Software License
Classifier: Operating System :: POSIX :: Linux
Classifier: Programming Language :: Python
Classifier: Programming Language :: Python :: 2
Classifier: Programming Language :: Python :: 2.7
Classifier: Programming Language :: Python :: 3
Classifier: Programming Language :: Python :: 3.5
Requires-Dist: pbr
Requires-Dist: pyapi-gitlab
Requires-Dist: PrettyTable
